odoo8_addon_purchase_fiscal_position_update-8.0.1.0.0.99.dev14-py3.8-nspkg.pth
odoo_addons/purchase_fiscal_position_update/__init__.py
odoo_addons/purchase_fiscal_position_update/__openerp__.py
odoo_addons/purchase_fiscal_position_update/purchase.py
odoo_addons/purchase_fiscal_position_update/i18n/de.po
odoo_addons/purchase_fiscal_position_update/i18n/es.po
odoo_addons/purchase_fiscal_position_update/i18n/eu.po
odoo_addons/purchase_fiscal_position_update/i18n/fi.po
odoo_addons/purchase_fiscal_position_update/i18n/fr.po
odoo_addons/purchase_fiscal_position_update/i18n/fr_FR.po
odoo_addons/purchase_fiscal_position_update/i18n/it.po
odoo_addons/purchase_fiscal_position_update/i18n/nl.po
odoo_addons/purchase_fiscal_position_update/i18n/pt_BR.po
odoo_addons/purchase_fiscal_position_update/i18n/purchase_fiscal_position_update.pot
odoo_addons/purchase_fiscal_position_update/i18n/ro.po
odoo_addons/purchase_fiscal_position_update/i18n/sl.po
odoo_addons/purchase_fiscal_position_update/i18n/tr.po
odoo_addons/purchase_fiscal_position_update/static/description/icon.png
odoo8_addon_purchase_fiscal_position_update-8.0.1.0.0.99.dev14.dist-info/METADATA
odoo8_addon_purchase_fiscal_position_update-8.0.1.0.0.99.dev14.dist-info/WHEEL
odoo8_addon_purchase_fiscal_position_update-8.0.1.0.0.99.dev14.dist-info/namespace_packages.txt
odoo8_addon_purchase_fiscal_position_update-8.0.1.0.0.99.dev14.dist-info/top_level.txt
odoo8_addon_purchase_fiscal_position_update-8.0.1.0.0.99.dev14.dist-info/RECORD
